dotbot/__about__.py
dotbot/__init__.py
dotbot/cli.py
dotbot/config.py
dotbot/context.py
dotbot/dispatcher.py
dotbot/plugin.py
dotbot/messenger/__init__.py
dotbot/messenger/color.py
dotbot/messenger/level.py
dotbot/messenger/messenger.py
dotbot/plugins/__init__.py
dotbot/plugins/clean.py
dotbot/plugins/create.py
dotbot/plugins/link.py
dotbot/plugins/shell.py
dotbot/util/__init__.py
dotbot/util/common.py
dotbot/util/module.py
dotbot/util/singleton.py
dotbot/util/string.py
dotbot-1.23.1.dist-info/METADATA
dotbot-1.23.1.dist-info/WHEEL
dotbot-1.23.1.dist-info/entry_points.txt
dotbot-1.23.1.dist-info/licenses/LICENSE.md
dotbot-1.23.1.dist-info/RECORD
