Metadata-Version: 2.4
Name: dotbot
Version: 1.23.1
Summary: A tool that bootstraps your dotfiles
Project-URL: homepage, https://github.com/anishathalye/dotbot
Project-URL: repository, https://github.com/anishathalye/dotbot.git
Project-URL: issues, https://github.com/anishathalye/dotbot/issues
Author-email: Anish Athalye <me@anishathalye.com>
License-File: LICENSE.md
Keywords: dotfiles
Classifier: Development Status :: 5 - Production/Stable
Classifier: Intended Audience :: Developers
Classifier: License :: OSI Approved :: MIT License
Classifier: Programming Language :: Python :: 3
Classifier: Topic :: Utilities
Requires-Python: >=3.7
Requires-Dist: pyyaml<7,>=6.0.1
